__init__.py
crudle/__init__.py
crudle/query_params_model.py
crudle/utils.py
crudle/adapters/__init__.py
crudle/adapters/sqlalchemy/__init__.py
crudle/adapters/sqlalchemy/adapter.py
crudle/adapters/sqlalchemy/helpers.py
crudle/adapters/sqlalchemy/query_builder.py
crudle/adapters/sqlalchemy/query_field.py
crudle-0.1.1.dist-info/METADATA
crudle-0.1.1.dist-info/WHEEL
crudle-0.1.1.dist-info/top_level.txt
crudle-0.1.1.dist-info/RECORD
