Metadata-Version: 2.4
Name: crudle
Version: 0.1.1
Summary: A CRUD library that simplifies working with SQLAlchemy
Requires-Python: >=3.13
Requires-Dist: pydantic>=2.11.9
Requires-Dist: sqlalchemy>=2.0.43
